Metadata-Version: 2.1
Name: pax3
Version: 0.5.9
Summary: A stateful pytree library for training neural networks.
Home-page: https://github.com/ntt123/pax
Author: Thông Nguyễn
License: UNKNOWN
Keywords: deep-learning,jax
Platform: UNKNOWN
Requires-Python: >=3.7
License-File: LICENSE
Requires-Dist: jax (>=0.2.21)
Requires-Dist: jmp (>=0.0.2)
Provides-Extra: test
Requires-Dist: chex ; extra == 'test'
Requires-Dist: dm-haiku ; extra == 'test'
Requires-Dist: fire ; extra == 'test'
Requires-Dist: opax ; extra == 'test'
Requires-Dist: pytest ; extra == 'test'
Requires-Dist: pytype ; extra == 'test'
Requires-Dist: tqdm ; extra == 'test'
